testprofiler/__init__.py
testprofiler/core.py
testprofiler/log_test.py
testprofiler/manipulate.py
testprofiler/serialise.py
testprofiler/testsuite.py
testprofiler/utils.py
testprofiler-1.0.1.dist-info/licenses/LICENSE
testprofiler-1.0.1.dist-info/METADATA
testprofiler-1.0.1.dist-info/WHEEL
testprofiler-1.0.1.dist-info/top_level.txt
testprofiler-1.0.1.dist-info/RECORD
